pycparserext/__init__.py
pycparserext/ext_c_generator.py
pycparserext/ext_c_lexer.py
pycparserext/ext_c_parser.py
pycparserext-2024.1.dist-info/METADATA
pycparserext-2024.1.dist-info/WHEEL
pycparserext-2024.1.dist-info/licenses/LICENSE
pycparserext-2024.1.dist-info/RECORD
