Metadata-Version: 2.3
Name: pycparserext
Version: 2024.1
Summary: Extensions for pycparser
Project-URL: Homepage, https://github.com/inducer/pycparserext
Author-email: Andreas Kloeckner <inform@tiker.net>
License: MIT
Classifier: Development Status :: 4 - Beta
Classifier: Intended Audience :: Developers
Classifier: Intended Audience :: Other Audience
Classifier: Intended Audience :: Science/Research
Classifier: License :: OSI Approved :: MIT License
Classifier: Natural Language :: English
Classifier: Programming Language :: Python
Classifier: Topic :: Utilities
Requires-Python: ~=3.8
Requires-Dist: ply>=3.4
Requires-Dist: pycparser~=2.21
